opal/__init__.py
opal/_version.py
opal/admin.py
opal/context_processors.py
opal/forms.py
opal/managers.py
opal/middleware.py
opal/models.py
opal/urls.py
opal/views.py
opal/core/__init__.py
opal/core/api.py
opal/core/application.py
opal/core/celery.py
opal/core/commandline.py
opal/core/detail.py
opal/core/discoverable.py
opal/core/episodes.py
opal/core/exceptions.py
opal/core/fields.py
opal/core/log.py
opal/core/lookuplists.py
opal/core/menus.py
opal/core/metadata.py
opal/core/patient_lists.py
opal/core/plugins.py
opal/core/scaffold.py
opal/core/schemas.py
opal/core/serialization.py
opal/core/subrecords.py
opal/core/tagging.py
opal/core/test.py
opal/core/test_runner.py
opal/core/views.py
opal/core/pathway/__init__.py
opal/core/pathway/api.py
opal/core/pathway/context_processors.py
opal/core/pathway/models.py
opal/core/pathway/pathways.py
opal/core/pathway/plugin.py
opal/core/pathway/steps.py
opal/core/pathway/urls.py
opal/core/pathway/views.py
opal/core/pathway/static/js/pathway/app.js
opal/core/pathway/static/js/pathway/directives.js
opal/core/pathway/static/js/pathway/controllers/default_single_step.js
opal/core/pathway/static/js/pathway/controllers/default_step.js
opal/core/pathway/static/js/pathway/controllers/modal_pathway_ctrl.js
opal/core/pathway/static/js/pathway/controllers/pathway_ctrl.js
opal/core/pathway/static/js/pathway/controllers/pathway_redirect.js
opal/core/pathway/static/js/pathway/services/pathway.js
opal/core/pathway/static/js/pathway/services/pathway_loader.js
opal/core/pathway/static/js/pathway/services/wizard_pathway.js
opal/core/pathway/static/js/test/app.test.js
opal/core/pathway/static/js/test/default_single_step.service.test.js
opal/core/pathway/static/js/test/directives.test.js
opal/core/pathway/static/js/test/modal_pathway.controller.test.js
opal/core/pathway/static/js/test/pathway.controller.test.js
opal/core/pathway/static/js/test/pathway.service.test.js
opal/core/pathway/static/js/test/pathway_loader.service.test.js
opal-0.18.3.dist-info/LICENSE.md
opal-0.18.3.dist-info/METADATA
opal-0.18.3.dist-info/WHEEL
opal-0.18.3.dist-info/entry_points.txt
opal-0.18.3.dist-info/top_level.txt
opal-0.18.3.dist-info/RECORD
