Metadata-Version: 2.1
Name: opal
Version: 0.18.3
Summary: A web framework for building highly usable healthcare applications.
Home-page: http://opal.openhealthcare.org.uk/
Author: Open Health Care UK
Author-email: hello@openhealthcare.org.uk
License: GPL3
Platform: UNKNOWN
Classifier: Programming Language :: Python
Classifier: Programming Language :: Python :: 3.5
Classifier: Programming Language :: Python :: 3.6
Classifier: Programming Language :: Python :: 3.7
Requires-Dist: ffs (>=0.0.8.2)
Requires-Dist: letter (==0.5)
Requires-Dist: Jinja2 (==2.10.1)
Requires-Dist: django (==2.0.13)
Requires-Dist: requests (==2.22.0)
Requires-Dist: django-axes (==1.7.0)
Requires-Dist: djangorestframework (==3.10.2)
Requires-Dist: django-reversion (==3.0.1)
Requires-Dist: django-compressor (==2.2)
Requires-Dist: python-dateutil (==2.8.0)
Requires-Dist: django-celery (==3.2.2)
Requires-Dist: celery (==3.1.25)
Requires-Dist: MarkupSafe (==1.1.1)
